django_celery_task_class/__init__.py
django_celery_task_class-0.1.0.dist-info/LICENSE
django_celery_task_class-0.1.0.dist-info/METADATA
django_celery_task_class-0.1.0.dist-info/WHEEL
django_celery_task_class-0.1.0.dist-info/RECORD
