Metadata-Version: 2.3
Name: django-celery-task-class
Version: 0.1.0
Summary: Django helpers for celery
License: MIT
Author: Enrico Barzetti
Author-email: 7615875+enricobarzetti@users.noreply.github.com
Requires-Python: >=3.9
Classifier: License :: OSI Approved :: MIT License
Classifier: Programming Language :: Python :: 3
Classifier: Programming Language :: Python :: 3.9
Classifier: Programming Language :: Python :: 3.10
Classifier: Programming Language :: Python :: 3.11
Classifier: Programming Language :: Python :: 3.12
Classifier: Programming Language :: Python :: 3.13
Requires-Dist: celery-task-class (>=0.1.0,<0.2.0)
Requires-Dist: django (>=3)
